zemberek/__init__.py
zemberek/examples.py
zemberek/core/__init__.py
zemberek/core/compression/__init__.py
zemberek/core/compression/lossy_int_lookup.py
zemberek/core/data/__init__.py
zemberek/core/data/compressed_weights.py
zemberek/core/data/weight_lookup.py
zemberek/core/hash/__init__.py
zemberek/core/hash/large_ngram_mphf.py
zemberek/core/hash/mphf.py
zemberek/core/hash/multi_level_mphf.py
zemberek/core/quantization/__init__.py
zemberek/core/quantization/float_lookup.py
zemberek/core/text/__init__.py
zemberek/core/text/text_util.py
zemberek/core/turkish/__init__.py
zemberek/core/turkish/hyphenation.py
zemberek/core/turkish/phonetic_attribute.py
zemberek/core/turkish/primary_pos.py
zemberek/core/turkish/root_attribute.py
zemberek/core/turkish/secondary_pos.py
zemberek/core/turkish/stem_and_ending.py
zemberek/core/turkish/turkic_letter.py
zemberek/core/turkish/turkish.py
zemberek/core/turkish/turkish_alphabet.py
zemberek/core/utils/__init__.py
zemberek/core/utils/thread_locks.py
zemberek/lm/__init__.py
zemberek/lm/lm_vocabulary.py
zemberek/lm/compression/__init__.py
zemberek/lm/compression/gram_data_array.py
zemberek/lm/compression/smooth_lm.py
zemberek/morphology/__init__.py
zemberek/morphology/turkish_morphology.py
zemberek/morphology/ambiguity/__init__.py
zemberek/morphology/ambiguity/ambiguity_resolver.py
zemberek/morphology/ambiguity/perceptron_ambiguity_resolver.py
zemberek/morphology/analysis/__init__.py
zemberek/morphology/analysis/attributes_helper.py
zemberek/morphology/analysis/informal_analysis_converter.py
zemberek/morphology/analysis/rule_based_analyzer.py
zemberek/morphology/analysis/search_path.py
zemberek/morphology/analysis/sentence_analysis.py
zemberek/morphology/analysis/sentence_word_analysis.py
zemberek/morphology/analysis/single_analysis.py
zemberek/morphology/analysis/surface_transitions.py
zemberek/morphology/analysis/unidentified_token_analyzer.py
zemberek/morphology/analysis/word_analysis.py
zemberek_python-0.2.3.dist-info/LICENSE
zemberek_python-0.2.3.dist-info/METADATA
zemberek_python-0.2.3.dist-info/WHEEL
zemberek_python-0.2.3.dist-info/top_level.txt
zemberek_python-0.2.3.dist-info/RECORD
