Metadata-Version: 2.1
Name: zemberek-python
Version: 0.2.3
Summary: Python port of open source text processing library for Turkish, zemberek-nlp
Home-page: https://www.loodos.com.tr/
Author: Loodos
License: Apache License 2.0
Classifier: Programming Language :: Python :: 3
Classifier: Operating System :: OS Independent
Requires-Python: >=3.7
License-File: LICENSE
Requires-Dist: antlr4-python3-runtime (==4.8)
Requires-Dist: numpy (>=1.19.0)
